metagen/__init__.py
metagen/framework/__init__.py
metagen/framework/facades.py
metagen/framework/connector/__init__.py
metagen/framework/connector/connector.py
metagen/framework/domain/__init__.py
metagen/framework/domain/bounds.py
metagen/framework/domain/core.py
metagen/framework/domain/literals.py
metagen/framework/domain/preconditions.py
metagen/framework/solution/__init__.py
metagen/framework/solution/base_solution.py
metagen/framework/solution/bounds.py
metagen/framework/solution/devsolution.py
metagen/framework/solution/literals.py
metagen/framework/solution/types/__init__.py
metagen/framework/solution/types/base.py
metagen/framework/solution/types/categorical.py
metagen/framework/solution/types/integer.py
metagen/framework/solution/types/real.py
metagen/framework/solution/types/structure.py
metagen/logging/__init__.py
metagen/logging/metagen_logger.py
metagen/logging/tensorboard_logger.py
metagen/metaheuristics/__init__.py
metagen/metaheuristics/base.py
metagen/metaheuristics/distributed_tools.py
metagen/metaheuristics/gamma_schedules.py
metagen/metaheuristics/import_helper.py
metagen/metaheuristics/tools.py
metagen/metaheuristics/cvoa/__init__.py
metagen/metaheuristics/cvoa/common_tools.py
metagen/metaheuristics/cvoa/cvoa_distributed.py
metagen/metaheuristics/cvoa/cvoa_local.py
metagen/metaheuristics/cvoa/distributed_launcher.py
metagen/metaheuristics/cvoa/distributed_tools.py
metagen/metaheuristics/cvoa/local_launcher.py
metagen/metaheuristics/cvoa/local_tools.py
metagen/metaheuristics/ga/__init__.py
metagen/metaheuristics/ga/ga.py
metagen/metaheuristics/ga/ga_tools.py
metagen/metaheuristics/ga/ssga.py
metagen/metaheuristics/mm/__init__.py
metagen/metaheuristics/mm/memetic.py
metagen/metaheuristics/mm/mm_tools.py
metagen/metaheuristics/rs/__init__.py
metagen/metaheuristics/rs/random_search.py
metagen/metaheuristics/sa/__init__.py
metagen/metaheuristics/sa/sa.py
metagen/metaheuristics/tpe/__init__.py
metagen/metaheuristics/tpe/tpe.py
pymetagen_datalabupo-0.2.1.dist-info/licenses/LICENSE
pymetagen_datalabupo-0.2.1.dist-info/METADATA
pymetagen_datalabupo-0.2.1.dist-info/WHEEL
pymetagen_datalabupo-0.2.1.dist-info/top_level.txt
pymetagen_datalabupo-0.2.1.dist-info/RECORD
