Metadata-Version: 2.4
Name: pymetagen-datalabupo
Version: 0.2.1
Summary: MetaGen: A framework for metaheuristic development and hyperparameter optimization in machine and deep learning.
Home-page: https://github.com/DataLabUPO/MetaGen
Author: Data Science & Big Data Rerearch Lab
Author-email: datalab@upo.es
Project-URL: Bug Tracker, https://github.com/DataLabUPO/MetaGen/issues
Classifier: Programming Language :: Python :: 3
Classifier: License :: OSI Approved :: MIT License
Classifier: Operating System :: OS Independent
Requires-Python: >=3.10
License-File: LICENSE
Requires-Dist: numpy>=1.21.0
Requires-Dist: scipy>=1.7.0
Provides-Extra: tensorboard
Requires-Dist: tensorboard; extra == "tensorboard"
Requires-Dist: tensorboardX; extra == "tensorboard"
Provides-Extra: all
Requires-Dist: tensorboard; extra == "all"
Requires-Dist: tensorboardX; extra == "all"
Requires-Dist: ray; extra == "all"
Provides-Extra: distributed
Requires-Dist: ray>=2.40.0; extra == "distributed"
Dynamic: license-file
